LICENSE
README.md
setup.py
src/llvm_installer/__init__.py
src/llvm_installer/__main__.py
src/llvm_installer/py.typed
src/llvm_installer/release_tags.json
src/llvm_installer.egg-info/PKG-INFO
src/llvm_installer.egg-info/SOURCES.txt
src/llvm_installer.egg-info/dependency_links.txt
src/llvm_installer.egg-info/entry_points.txt
src/llvm_installer.egg-info/requires.txt
src/llvm_installer.egg-info/top_level.txt