Metadata-Version: 2.1
Name: llvm-installer
Version: 1.4.12
Summary: Allows installing pre-built LLVM packages for various operating systems
Home-page: https://github.com/yugabyte/llvm-installer
Author: Mikhail Bautin
Author-email: mbautin@users.noreply.github.com
License: UNKNOWN
Platform: UNKNOWN
Provides-Extra: dev
License-File: LICENSE
